kiras/__init__.py
kiras/exact_code_strings.py
kiras/exact_prac1.py
kiras/exact_prac3.py
kiras/exact_prac4.py
kiras/exact_prac5.py
kiras/exact_prac7.py
kiras/exact_prac8.py
kiras-0.1.1.dist-info/licenses/LICENSE
kiras-0.1.1.dist-info/METADATA
kiras-0.1.1.dist-info/WHEEL
kiras-0.1.1.dist-info/top_level.txt
kiras-0.1.1.dist-info/RECORD
